pandasql/__init__.py
pandasql/sqldf.py
pandasql/data/births.csv
pandasql/data/births_by_month.csv
pandasql/data/meat.csv
pandasql/tests/__init__.py
pandasql/tests/test_pandasql.py
pandasql/tests/test_utils.py
pandasql3-0.7.3.dist-info/AUTHORS.md
pandasql3-0.7.3.dist-info/LICENSE.txt
pandasql3-0.7.3.dist-info/METADATA
pandasql3-0.7.3.dist-info/WHEEL
pandasql3-0.7.3.dist-info/top_level.txt
pandasql3-0.7.3.dist-info/RECORD
