Metadata-Version: 2.1
Name: pandasql3
Version: 0.7.3
Summary: sqldf for pandas
Home-page: https://github.com/dunakeyr/pandasql3/
Author: Greg Lamp
Author-email: greg@yhathq.com
License: MIT
Platform: UNKNOWN
Classifier: License :: OSI Approved :: MIT License
Requires-Dist: numpy
Requires-Dist: pandas
Requires-Dist: sqlalchemy
